Metadata-Version: 1.0
Name: crunch
Version: 0.0.2.1
Summary: Command line tool download and upload files
Home-page: https://github.com/kracekumar/crunch
Author: kracekumar
Author-email: me@kracekumar.com
License: ISC
Platform: UNKNOWN
Classifier: Development Status :: 1 - Planning
Classifier: Environment :: Console
Classifier: Intended Audience :: Developers
Classifier: Intended Audience :: End Users/Desktop
Classifier: Intended Audience :: System Administrators
Classifier: Natural Language :: English
Classifier: License :: OSI Approved :: ISC License (ISCL)
Classifier: Programming Language :: Python
Classifier: Programming Language :: Python :: 2
Classifier: Programming Language :: Python :: 2.5
Classifier: Programming Language :: Python :: 2.6
Classifier: Programming Language :: Python :: 2.7
Classifier: Topic :: Terminals :: Terminal Emulators/X Terminals
